SPerATo-0.9.2.data/scripts/monitoring-plots-hkhlr
sperato/__init__.py
sperato/aux_plots.py
sperato/aux_slurm.py
sperato/cluster.py
sperato/email.py
sperato/errors.py
sperato/filters.py
sperato/global_conf.py
sperato/hkhlr.py
sperato/output.py
sperato/plots.py
sperato/slurm.py
sperato/speratolist.py
sperato/version.py
sperato/ui/__init__.py
sperato/ui/cl.py
sperato/ui/conffile.py
SPerATo-0.9.2.dist-info/COPYING
SPerATo-0.9.2.dist-info/METADATA
SPerATo-0.9.2.dist-info/WHEEL
SPerATo-0.9.2.dist-info/entry_points.txt
SPerATo-0.9.2.dist-info/top_level.txt
SPerATo-0.9.2.dist-info/RECORD
