Metadata-Version: 2.1
Name: SPerATo
Version: 0.9.2
Summary: Slurm jobs Performance Analysis Tool
Home-page: https://itp.uni-frankfurt.de/~palao/software/SPerATo
Author: David Palao
Author-email: palao@csc.uni-frankfurt.de
License: GNU General Public License (GPLv3)
Platform: GNU/Linux
Classifier: Development Status :: 4 - Beta
Classifier: Environment :: Console
Classifier: Intended Audience :: System Administrators
Classifier: License :: OSI Approved :: GNU General Public License v3 (GPLv3)
Classifier: Natural Language :: English
Classifier: Operating System :: POSIX :: Linux
Classifier: Programming Language :: Python :: 3
Classifier: Programming Language :: Python :: 3.6
Classifier: Programming Language :: Python :: Implementation :: CPython
Classifier: Topic :: System :: Monitoring
Provides: sperato
Requires-Dist: numpy
Requires-Dist: matplotlib
